LICENSE.txt
MANIFEST.in
README.md
setup.cfg
setup.py
RdQxbAPI/RdQxbAPI.pyd
RdQxbAPI/__init__.py
RdQxbAPI/optionDb.pyd
RdQxbAPI.egg-info/PKG-INFO
RdQxbAPI.egg-info/SOURCES.txt
RdQxbAPI.egg-info/dependency_links.txt
RdQxbAPI.egg-info/top_level.txt
RdQxbAPI/Function/QxbAPIchange.pyd
RdQxbAPI/Function/QxbAPIkgr.pyd
RdQxbAPI/Function/QxbAPIphone.pyd
RdQxbAPI/Function/QxbAPIqylt.pyd
RdQxbAPI/Function/QxbAPIysglf.pyd
RdQxbAPI/Function/QxbAPIzyrytz.pyd
RdQxbAPI/Function/__init__.py
RdQxbAPI/UI/__init__.py
RdQxbAPI/UI/qxbUI.pyd